acmp_libs/__init__.py
acmp_libs/core/__init__.py
acmp_libs/core/errors/__init__.py
acmp_libs/core/errors/custom_exception_handler.py
acmp_libs/monitoring/__init__.py
acmp_libs/platform/__init__.py
divide/__init__.py
divide/by_three.py
multiply/__init__.py
multiply/by_three.py
tests/__init__.py
tests/test_divide_by_three.py
tests/test_multiply_by_three.py
acmp_utils-23.12.0.dist-info/LICENSE.txt
acmp_utils-23.12.0.dist-info/METADATA
acmp_utils-23.12.0.dist-info/WHEEL
acmp_utils-23.12.0.dist-info/top_level.txt
acmp_utils-23.12.0.dist-info/RECORD
