Metadata-Version: 2.1
Name: acmp_utils
Version: 23.12.0
Summary: Power packed utils repository to be used by ACMP teams for day to day development.
Home-page: https://gitlab.corp.amdocs.com/atomiq/cloud/acmp_libs
Author: Pradeepta Dinda
Author-email: hd40910@gmail.com
Project-URL: Bug Tracker, https://gitlab.corp.amdocs.com/atomiq/cloud/acmp_libs/-/issues
Project-URL: repository, https://gitlab.corp.amdocs.com/atomiq/cloud/acmp_libs
Classifier: Programming Language :: Python :: 3
Classifier: License :: OSI Approved :: MIT License
Classifier: Operating System :: OS Independent
Requires-Python: >=3.6
License-File: LICENSE.txt
